calflops/__init__.py
calflops/calculate_pipline.py
calflops/estimate.py
calflops/flops_counter.py
calflops/flops_counter_hf.py
calflops/pytorch_ops.py
calflops/utils.py
calflops2-0.1.2.dist-info/licenses/LICENSE
calflops2-0.1.2.dist-info/METADATA
calflops2-0.1.2.dist-info/WHEEL
calflops2-0.1.2.dist-info/top_level.txt
calflops2-0.1.2.dist-info/RECORD
