Metadata-Version: 2.4
Name: calflops2
Version: 0.1.2
Summary: A tool to calculate FLOPs and Params for neural networks
Home-page: https://github.com/andrijdavid/calculate-flops.pytorch
Author: Andrij David
Author-email: david@andrij.me
Classifier: Programming Language :: Python :: 3
Classifier: License :: OSI Approved :: Apache Software License
Classifier: Operating System :: OS Independent
Requires-Python: >=3.6
License-File: LICENSE
Requires-Dist: torch
Requires-Dist: torchvision
Requires-Dist: transformers
Requires-Dist: numpy
Requires-Dist: accelerate
Dynamic: author
Dynamic: author-email
Dynamic: classifier
Dynamic: description
Dynamic: description-content-type
Dynamic: home-page
Dynamic: license-file
Dynamic: requires-dist
Dynamic: requires-python
Dynamic: summary
